sxml/__init__.py
sxml/__main__.py
sxml/cli.py
sxml/operators.py
sxml/options.py
sxml/query.py
sxml/utils.py
sxml/yaml_helpers.py
sxml/methods/__init__.py
sxml/methods/html.py
sxml-0.1.5.dist-info/LICENSE
sxml-0.1.5.dist-info/METADATA
sxml-0.1.5.dist-info/WHEEL
sxml-0.1.5.dist-info/entry_points.txt
sxml-0.1.5.dist-info/top_level.txt
sxml-0.1.5.dist-info/zip-safe
sxml-0.1.5.dist-info/RECORD
