Metadata-Version: 2.1
Name: sxml
Version: 0.1.5
Summary: Simple lxml pipeline
Home-page: UNKNOWN
License: MIT
Project-URL: Homepage, https://github.com/vmstarchenko/sxml
Keywords: lxml
Platform: any
Classifier: Development Status :: 3 - Alpha
Classifier: Intended Audience :: Developers
Classifier: License :: OSI Approved :: MIT License
Classifier: Programming Language :: Python
Classifier: Programming Language :: Python :: 3
Classifier: Programming Language :: Python :: 3.6
Classifier: Programming Language :: Python :: 3.7
Classifier: Programming Language :: Python :: 3.8
Classifier: Programming Language :: Python :: 3.9
Classifier: Programming Language :: Python :: 3.9
Classifier: Programming Language :: Python :: Implementation
Classifier: Programming Language :: Python :: Implementation :: IronPython
Classifier: Programming Language :: Python :: Implementation :: PyPy
License-File: LICENSE
Requires-Dist: PyYAML
Requires-Dist: lxml
Requires-Dist: cssselect
Requires-Dist: jsonpath-ng
Requires-Dist: dateparser
Requires-Dist: beautifulsoup4
Requires-Dist: extruct
